[
    {
        "year_manufacture": 2020,
        "years": 5,
        "make": "toyota",
        "model": "Toyota RAV4 XLE",
        "mileage": 86379.0,
        "stock_type": "Used",
        "interior_color": "–",
        "exterior_color": "Silver Sky Metallic",
        "drive_train": "All-wheel Drive",
        "mpg": "27–33 Based on EPA mileage ratings. Use for comparison purposes only. Actual mileage will vary depending on driving conditions, driving habits, vehicle maintenance, and other factors.",
        "fuel_type": "Gasoline",
        "transmission": "Automatic",
        "engine": "Dynamic Force 2.5L I-4 port/direct injection, DOHC, VVT-iE varia",
        "price_USD": 22973.0,
        "url": "https://cars.com/vehicledetail/8b14fbad-0caa-45d4-a677-cd96f689e02c/?attribution_type=premier"
    },
    {
        "year_manufacture": 2023,
        "years": 2,
        "make": "toyota",
        "model": "Toyota RAV4 Hybrid XLE Premium",
        "mileage": 29465.0,
        "stock_type": "Certified",
        "interior_color": "Ash",
        "exterior_color": "Lunar Rock",
        "drive_train": "All-wheel Drive",
        "mpg": "41–38 Based on EPA mileage ratings. Use for comparison purposes only. Actual mileage will vary depending on driving conditions, driving habits, vehicle maintenance, and other factors.",
        "fuel_type": "Hybrid",
        "transmission": "CVT Transmission",
        "engine": "Dynamic Force 2.5L I-4 port/direct injection, DOHC, VVT-i variab",
        "price_USD": 37990.0,
        "url": "https://cars.com/vehicledetail/1fa9fe40-ecec-4479-84b6-a93c7bb4a190/"
    },
    {
        "year_manufacture": 2023,
        "years": 2,
        "make": "toyota",
        "model": "Toyota Sequoia Platinum",
        "mileage": 15246.0,
        "stock_type": "Used",
        "interior_color": "Black",
        "exterior_color": "Magnetic Gray Metallic",
        "drive_train": "Four-wheel Drive",
        "mpg": "19–22 Based on EPA mileage ratings. Use for comparison purposes only. Actual mileage will vary depending on driving conditions, driving habits, vehicle maintenance, and other factors.",
        "fuel_type": "Gasoline",
        "transmission": "Automatic",
        "engine": "I-FORCE MAX 3.4L V-6 port/direct injection, DOHC, variable valve",
        "price_USD": 69789.0,
        "url": "https://cars.com/vehicledetail/4707555f-b108-41c1-926a-8f6c6f500735/"
    },
    {
        "year_manufacture": 2024,
        "years": 1,
        "make": "toyota",
        "model": "Toyota RAV4 Hybrid XLE",
        "mileage": 20753.0,
        "stock_type": "Used",
        "interior_color": "Black",
        "exterior_color": "Midnight Black Metallic",
        "drive_train": "All-wheel Drive",
        "mpg": "41–38 Based on EPA mileage ratings. Use for comparison purposes only. Actual mileage will vary depending on driving conditions, driving habits, vehicle maintenance, and other factors.",
        "fuel_type": "Hybrid",
        "transmission": "eCVT",
        "engine": "Dynamic Force 2.5L I-4 port/direct injection, DOHC, VVT-i variab",
        "price_USD": 35181.0,
        "url": "https://cars.com/vehicledetail/74ff50e5-f64f-4f3c-9e6b-36c145f107e4/"
    },
    {
        "year_manufacture": 2019,
        "years": 6,
        "make": "toyota",
        "model": "Toyota Camry Hybrid LE",
        "mileage": 107732.0,
        "stock_type": "Used",
        "interior_color": "–",
        "exterior_color": "Celestial Silver Metallic",
        "drive_train": "Front-wheel Drive",
        "mpg": "51–53 Based on EPA mileage ratings. Use for comparison purposes only. Actual mileage will vary depending on driving conditions, driving habits, vehicle maintenance, and other factors.",
        "fuel_type": "Hybrid",
        "transmission": "eCVT",
        "engine": "Dynamic Force 2.5L I-4 port/direct injection, DOHC, VVT-iE/VVT-i",
        "price_USD": 18500.0,
        "url": "https://cars.com/vehicledetail/af954d16-9110-4dea-8461-01122f7cd4e8/"
    },
    {
        "year_manufacture": 2022,
        "years": 3,
        "make": "toyota",
        "model": "Toyota RAV4 Hybrid SE",
        "mileage": 32824.0,
        "stock_type": "Used",
        "interior_color": "Black",
        "exterior_color": "Black",
        "drive_train": "All-wheel Drive",
        "mpg": "41–38 Based on EPA mileage ratings. Use for comparison purposes only. Actual mileage will vary depending on driving conditions, driving habits, vehicle maintenance, and other factors.",
        "fuel_type": "Hybrid",
        "transmission": "Variable",
        "engine": "Dynamic Force 2.5L I-4 port/direct injection, DOHC, VVT-i variab",
        "price_USD": 34566.0,
        "url": "https://cars.com/vehicledetail/24431bd8-d6e5-49fb-a725-56c5fefc68a9/"
    },
    {
        "year_manufacture": 2015,
        "years": 10,
        "make": "toyota",
        "model": "Toyota Prius Three",
        "mileage": 107637.0,
        "stock_type": "Used",
        "interior_color": "Dark Gray",
        "exterior_color": "Classic Silver Metallic",
        "drive_train": "Front-wheel Drive",
        "mpg": "51–48 Based on EPA mileage ratings. Use for comparison purposes only. Actual mileage will vary depending on driving conditions, driving habits, vehicle maintenance, and other factors.",
        "fuel_type": "Hybrid",
        "transmission": "Automatic CVT",
        "engine": "1.8L I4 16V MPFI DOHC Hybrid",
        "price_USD": 12000.0,
        "url": "https://cars.com/vehicledetail/e7346e9e-5f2e-499e-b927-1a581a592b98/"
    },
    {
        "year_manufacture": 2016,
        "years": 9,
        "make": "toyota",
        "model": "Toyota 4Runner SR5",
        "mileage": 179318.0,
        "stock_type": "Used",
        "interior_color": "Black/Graphite",
        "exterior_color": "Super White",
        "drive_train": "Four-wheel Drive",
        "mpg": "17–21 Based on EPA mileage ratings. Use for comparison purposes only. Actual mileage will vary depending on driving conditions, driving habits, vehicle maintenance, and other factors.",
        "fuel_type": "Gasoline",
        "transmission": "Automatic",
        "engine": "4L V-6 DOHC, VVT-i variable valve control, regular unleaded, eng",
        "price_USD": 19057.0,
        "url": "https://cars.com/vehicledetail/8db05cf9-3a10-4e68-852d-7eb117aac157/"
    },
    {
        "year_manufacture": 2022,
        "years": 3,
        "make": "toyota",
        "model": "Toyota Corolla Hybrid LE",
        "mileage": 40274.0,
        "stock_type": "Used",
        "interior_color": "Gray",
        "exterior_color": "White",
        "drive_train": "Front-wheel Drive",
        "mpg": "53–52 Based on EPA mileage ratings. Use for comparison purposes only. Actual mileage will vary depending on driving conditions, driving habits, vehicle maintenance, and other factors.",
        "fuel_type": "Hybrid",
        "transmission": "Automatic CVT",
        "engine": "1.8L I4 16V MPFI DOHC Hybrid",
        "price_USD": 20896.0,
        "url": "https://cars.com/vehicledetail/af0fc3eb-e03a-450c-88df-bb852c61ff8e/"
    },
    {
        "year_manufacture": 2023,
        "years": 2,
        "make": "toyota",
        "model": "Toyota Highlander Hybrid LE",
        "mileage": 33539.0,
        "stock_type": "Certified",
        "interior_color": "Black",
        "exterior_color": "Celestial Silver Metallic",
        "drive_train": "All-wheel Drive",
        "mpg": "35–35 Based on EPA mileage ratings. Use for comparison purposes only. Actual mileage will vary depending on driving conditions, driving habits, vehicle maintenance, and other factors.",
        "fuel_type": "Hybrid",
        "transmission": "Automatic",
        "engine": "2.5L I-4 port/direct injection, DOHC, VVT-iE/VVT-i variable valv",
        "price_USD": 36997.0,
        "url": "https://cars.com/vehicledetail/7581e878-39a7-4970-908f-f0d2ec733435/"
    },
    {
        "year_manufacture": 2022,
        "years": 3,
        "make": "toyota",
        "model": "Toyota Supra",
        "mileage": 10287.0,
        "stock_type": "Used",
        "interior_color": "BLACK",
        "exterior_color": "Yellow",
        "drive_train": "Rear-wheel Drive",
        "mpg": "24–31 Based on EPA mileage ratings. Use for comparison purposes only. Actual mileage will vary depending on driving conditions, driving habits, vehicle maintenance, and other factors.",
        "fuel_type": "Gasoline",
        "transmission": "Automatic",
        "engine": "Turbo Gas",
        "price_USD": 54998.0,
        "url": "https://cars.com/vehicledetail/e037c8fc-b3e1-4aad-b83b-4307b7a43ebf/"
    },
    {
        "year_manufacture": 1998,
        "years": 27,
        "make": "toyota",
        "model": "Toyota Celica GT",
        "mileage": 95000.0,
        "stock_type": "Used",
        "interior_color": "Black",
        "exterior_color": "Black",
        "drive_train": "Front-wheel Drive",
        "mpg": null,
        "fuel_type": "Gasoline",
        "transmission": "A/T",
        "engine": "130.0HP 2.2L 4 Cylinder Engine Gasoline Fuel",
        "price_USD": 6900.0,
        "url": "https://cars.com/vehicledetail/80b7f82a-aeb9-4fda-8800-dbb45ade2300/"
    },
    {
        "year_manufacture": 2024,
        "years": 1,
        "make": "toyota",
        "model": "Toyota Venza Nightshade Edition",
        "mileage": 15058.0,
        "stock_type": "Certified",
        "interior_color": "Black",
        "exterior_color": "Pearl",
        "drive_train": "All-wheel Drive",
        "mpg": "40–37 Based on EPA mileage ratings. Use for comparison purposes only. Actual mileage will vary depending on driving conditions, driving habits, vehicle maintenance, and other factors.",
        "fuel_type": "Gasoline",
        "transmission": "Continuously Variable (ECVT)",
        "engine": "2.5L I-4 port/direct injection, DOHC, variable valve control, re",
        "price_USD": 39995.0,
        "url": "https://cars.com/vehicledetail/206145ea-68f9-4b48-b599-51c1b33ee00b/"
    },
    {
        "year_manufacture": 2023,
        "years": 2,
        "make": "toyota",
        "model": "Toyota 4Runner SR5",
        "mileage": 35544.0,
        "stock_type": "Used",
        "interior_color": "Black / Graphite",
        "exterior_color": "White",
        "drive_train": "Four-wheel Drive",
        "mpg": "16–19 Based on EPA mileage ratings. Use for comparison purposes only. Actual mileage will vary depending on driving conditions, driving habits, vehicle maintenance, and other factors.",
        "fuel_type": "Gasoline",
        "transmission": "5-Speed Automatic",
        "engine": "4.0L V6 24V MPFI DOHC",
        "price_USD": 37995.0,
        "url": "https://cars.com/vehicledetail/19813fd7-029c-4830-94f3-4b00304a900e/"
    },
    {
        "year_manufacture": 2023,
        "years": 2,
        "make": "toyota",
        "model": "Toyota Venza LE",
        "mileage": 30902.0,
        "stock_type": "Certified",
        "interior_color": "Black",
        "exterior_color": "Black",
        "drive_train": "All-wheel Drive",
        "mpg": "40–37 Based on EPA mileage ratings. Use for comparison purposes only. Actual mileage will vary depending on driving conditions, driving habits, vehicle maintenance, and other factors.",
        "fuel_type": "Gasoline",
        "transmission": "Automatic",
        "engine": "2.5L I-4 port/direct injection, DOHC, variable valve control, re",
        "price_USD": 30955.0,
        "url": "https://cars.com/vehicledetail/3e663181-45c7-4390-b041-5d746a74fead/"
    },
    {
        "year_manufacture": 2017,
        "years": 8,
        "make": "toyota",
        "model": "Toyota Tundra SR5",
        "mileage": 126521.0,
        "stock_type": "Used",
        "interior_color": "Black",
        "exterior_color": "Black",
        "drive_train": "Rear-wheel Drive",
        "mpg": "15–19 Based on EPA mileage ratings. Use for comparison purposes only. Actual mileage will vary depending on driving conditions, driving habits, vehicle maintenance, and other factors.",
        "fuel_type": "Gasoline",
        "transmission": "Automatic",
        "engine": "I-FORCE 4.6L V-8 DOHC, VVT-i variable valve control, regular unl",
        "price_USD": 24950.0,
        "url": "https://cars.com/vehicledetail/fad56c7e-103c-4670-9b50-c1b72af2d464/"
    },
    {
        "year_manufacture": 2021,
        "years": 4,
        "make": "toyota",
        "model": "Toyota Venza LE",
        "mileage": 43644.0,
        "stock_type": "Used",
        "interior_color": "Black",
        "exterior_color": "Ruby Flare Pearl",
        "drive_train": "All-wheel Drive",
        "mpg": "40–37 Based on EPA mileage ratings. Use for comparison purposes only. Actual mileage will vary depending on driving conditions, driving habits, vehicle maintenance, and other factors.",
        "fuel_type": "Gasoline",
        "transmission": "Continuously Variable (ECVT)",
        "engine": "2.5L I-4 port/direct injection, DOHC, variable valve control, re",
        "price_USD": 28989.0,
        "url": "https://cars.com/vehicledetail/c8f7befd-17fe-49ae-8c4d-59079c89a0cd/"
    },
    {
        "year_manufacture": 2005,
        "years": 20,
        "make": "toyota",
        "model": "Toyota Camry Solara SLE V6",
        "mileage": 137600.0,
        "stock_type": "Used",
        "interior_color": "Gray",
        "exterior_color": "Blue",
        "drive_train": "Front-wheel Drive",
        "mpg": null,
        "fuel_type": "Gasoline",
        "transmission": "5-Speed A/T",
        "engine": "225.0HP 3.3L V6 Cylinder Engine Gasoline Fuel",
        "price_USD": 5250.0,
        "url": "https://cars.com/vehicledetail/2bf23665-0543-414e-bb70-665836f27538/"
    },
    {
        "year_manufacture": 2019,
        "years": 6,
        "make": "toyota",
        "model": "Toyota Yaris Sedan XLE",
        "mileage": 112138.0,
        "stock_type": "Used",
        "interior_color": "Black",
        "exterior_color": "Silver",
        "drive_train": "Front-wheel Drive",
        "mpg": "32–40 Based on EPA mileage ratings. Use for comparison purposes only. Actual mileage will vary depending on driving conditions, driving habits, vehicle maintenance, and other factors.",
        "fuel_type": "Gasoline",
        "transmission": "6-Speed Automatic",
        "engine": "1.5L I4 16V GDI DOHC",
        "price_USD": 9499.0,
        "url": "https://cars.com/vehicledetail/39629a79-65fc-4942-bdcc-723e48d1380d/"
    },
    {
        "year_manufacture": 2022,
        "years": 3,
        "make": "toyota",
        "model": "Toyota Mirai Base",
        "mileage": 27079.0,
        "stock_type": "Used",
        "interior_color": "Black w/Silver",
        "exterior_color": "–",
        "drive_train": "Rear-wheel Drive",
        "mpg": null,
        "fuel_type": null,
        "transmission": "1-Speed Automatic",
        "engine": "Electric Motor",
        "price_USD": 9979.0,
        "url": "https://cars.com/vehicledetail/6fc65ccd-50b2-4394-a185-8e06b07f3410/"
    },
    {
        "year_manufacture": 2017,
        "years": 8,
        "make": "toyota",
        "model": "Toyota Yaris L",
        "mileage": 77953.0,
        "stock_type": "Used",
        "interior_color": "Black",
        "exterior_color": "Gray",
        "drive_train": "Front-wheel Drive",
        "mpg": "30 Based on EPA mileage ratings. Use for comparison purposes only. Actual mileage will vary depending on driving conditions, driving habits, vehicle maintenance, and other factors.",
        "fuel_type": "Gasoline",
        "transmission": "Manual",
        "engine": "1.5L I4 16V MPFI DOHC",
        "price_USD": 13701.0,
        "url": "https://cars.com/vehicledetail/6b9f0a9c-471b-4c39-9e39-e6f7797efb9a/"
    }
]