[
    {
        "year_manufacture": 2014,
        "years": 11,
        "make": "mini",
        "model": "MINI Paceman Cooper",
        "mileage": 93057.0,
        "stock_type": "Used",
        "interior_color": "Black",
        "exterior_color": "Gray",
        "drive_train": "Front-wheel Drive",
        "mpg": "28–35 Based on EPA mileage ratings. Use for comparison purposes only. Actual mileage will vary depending on driving conditions, driving habits, vehicle maintenance, and other factors.",
        "fuel_type": "Gasoline",
        "transmission": "6-Speed Automatic",
        "engine": "1.6L I4 16V MPFI DOHC",
        "price_USD": 8995.0,
        "url": "https://cars.com/vehicledetail/c572fab5-31ff-44f9-af58-656fdc1bc3e1/"
    },
    {
        "year_manufacture": 2012,
        "years": 13,
        "make": "mini",
        "model": "MINI Cooper Countryman Base",
        "mileage": 120853.0,
        "stock_type": "Used",
        "interior_color": "Black",
        "exterior_color": "Yellow",
        "drive_train": "Front-wheel Drive",
        "mpg": "26–32 Based on EPA mileage ratings. Use for comparison purposes only. Actual mileage will vary depending on driving conditions, driving habits, vehicle maintenance, and other factors.",
        "fuel_type": "Gasoline",
        "transmission": "Manual 6-Speed",
        "engine": "1.6L I-4 gasoline direct injection, DOHC, variable valve control",
        "price_USD": 5999.0,
        "url": "https://cars.com/vehicledetail/87e79269-f517-43b3-8cfd-091b0cafeb36/"
    },
    {
        "year_manufacture": 2024,
        "years": 1,
        "make": "mini",
        "model": "MINI Countryman Cooper S ALL4",
        "mileage": 24873.0,
        "stock_type": "Used",
        "interior_color": "–",
        "exterior_color": "Gray",
        "drive_train": "All-wheel Drive",
        "mpg": "23–31 Based on EPA mileage ratings. Use for comparison purposes only. Actual mileage will vary depending on driving conditions, driving habits, vehicle maintenance, and other factors.",
        "fuel_type": "Gasoline",
        "transmission": "Automatic",
        "engine": "2L I-4 gasoline direct injection, DOHC, variable valve control,",
        "price_USD": 25644.0,
        "url": "https://cars.com/vehicledetail/f88de05b-7ee0-4aa8-b27c-a2f6406cdb9c/"
    },
    {
        "year_manufacture": 2024,
        "years": 1,
        "make": "mini",
        "model": "MINI Convertible Cooper S",
        "mileage": 17559.0,
        "stock_type": "Used",
        "interior_color": "Carbon Black",
        "exterior_color": "British Racing Green IV Metallic",
        "drive_train": "Front-wheel Drive",
        "mpg": "27–33 Based on EPA mileage ratings. Use for comparison purposes only. Actual mileage will vary depending on driving conditions, driving habits, vehicle maintenance, and other factors.",
        "fuel_type": "Gasoline",
        "transmission": "Manual",
        "engine": "2L I-4 gasoline direct injection, DOHC, variable valve control,",
        "price_USD": 26500.0,
        "url": "https://cars.com/vehicledetail/e2c0262f-519b-4473-b1ed-7eb934615dee/"
    },
    {
        "year_manufacture": 2023,
        "years": 2,
        "make": "mini",
        "model": "MINI Countryman Cooper S",
        "mileage": 14172.0,
        "stock_type": "Used",
        "interior_color": "Satellite Grey",
        "exterior_color": "Island Blue Metallic",
        "drive_train": "Front-wheel Drive",
        "mpg": "24–33 Based on EPA mileage ratings. Use for comparison purposes only. Actual mileage will vary depending on driving conditions, driving habits, vehicle maintenance, and other factors.",
        "fuel_type": "Gasoline",
        "transmission": "7-Speed Automatic with Auto-Shift",
        "engine": "2.0L I4 16V GDI DOHC Turbo",
        "price_USD": 27915.0,
        "url": "https://cars.com/vehicledetail/101be015-c367-4fa7-a418-e69660931e37/"
    },
    {
        "year_manufacture": 2011,
        "years": 14,
        "make": "mini",
        "model": "MINI Cooper S Base",
        "mileage": 102977.0,
        "stock_type": "Used",
        "interior_color": "Black",
        "exterior_color": "Pepper White",
        "drive_train": "Front-wheel Drive",
        "mpg": "26–36 Based on EPA mileage ratings. Use for comparison purposes only. Actual mileage will vary depending on driving conditions, driving habits, vehicle maintenance, and other factors.",
        "fuel_type": "Gasoline",
        "transmission": "Getrag 6-Speed Manual with Overdrive",
        "engine": "1.6L I-4 gasoline direct injection, DOHC, variable valve control",
        "price_USD": 7995.0,
        "url": "https://cars.com/vehicledetail/53ccf63e-a37b-4ca2-a647-bceac70e837e/"
    },
    {
        "year_manufacture": 2010,
        "years": 15,
        "make": "mini",
        "model": "MINI Cooper S Base",
        "mileage": 96917.0,
        "stock_type": "Used",
        "interior_color": "Grey/Carbon Black",
        "exterior_color": "British Racing Green Metallic",
        "drive_train": "Front-wheel Drive",
        "mpg": "24–34 Based on EPA mileage ratings. Use for comparison purposes only. Actual mileage will vary depending on driving conditions, driving habits, vehicle maintenance, and other factors.",
        "fuel_type": "Gasoline",
        "transmission": "Automatic",
        "engine": "1.6L I-4 gasoline direct injection, DOHC, variable valve control",
        "price_USD": 7594.0,
        "url": "https://cars.com/vehicledetail/96a06246-ba96-46c7-8574-2ac1bfae96d7/"
    },
    {
        "year_manufacture": 2017,
        "years": 8,
        "make": "mini",
        "model": "MINI Clubman Cooper ALL4",
        "mileage": 124146.0,
        "stock_type": "Used",
        "interior_color": "–",
        "exterior_color": "Pepper White",
        "drive_train": "All-wheel Drive",
        "mpg": "22–32.0 Based on EPA mileage ratings. Use for comparison purposes only. Actual mileage will vary depending on driving conditions, driving habits, vehicle maintenance, and other factors.",
        "fuel_type": "Gasoline",
        "transmission": "Automatic",
        "engine": "1.5L I-3 gasoline direct injection, DOHC, variable valve control",
        "price_USD": 11993.0,
        "url": "https://cars.com/vehicledetail/d743cb67-e544-4e0e-b81e-f8449648c957/"
    },
    {
        "year_manufacture": 2012,
        "years": 13,
        "make": "mini",
        "model": "MINI Cooper S Base",
        "mileage": 117283.0,
        "stock_type": "Used",
        "interior_color": "Black",
        "exterior_color": "Blue",
        "drive_train": "Front-wheel Drive",
        "mpg": null,
        "fuel_type": "Gasoline",
        "transmission": "6-Speed M/T",
        "engine": "181.0HP 1.6L 4 Cylinder Engine Gasoline Fuel",
        "price_USD": 6999.0,
        "url": "https://cars.com/vehicledetail/fd083964-00f0-4f6d-a51d-2ce365876833/"
    },
    {
        "year_manufacture": 2024,
        "years": 1,
        "make": "mini",
        "model": "MINI Countryman Cooper S",
        "mileage": 6741.0,
        "stock_type": "Used",
        "interior_color": "Satellite Grey",
        "exterior_color": "Midnight Black II",
        "drive_train": "Front-wheel Drive",
        "mpg": "24–33 Based on EPA mileage ratings. Use for comparison purposes only. Actual mileage will vary depending on driving conditions, driving habits, vehicle maintenance, and other factors.",
        "fuel_type": "Gasoline",
        "transmission": "Automatic",
        "engine": "2L I-4 gasoline direct injection, DOHC, variable valve control,",
        "price_USD": 32988.0,
        "url": "https://cars.com/vehicledetail/2087d399-a00a-4758-b735-cac06d67160a/"
    },
    {
        "year_manufacture": 2021,
        "years": 4,
        "make": "mini",
        "model": "MINI Countryman Cooper S ALL4",
        "mileage": 48844.0,
        "stock_type": "Used",
        "interior_color": "–",
        "exterior_color": "–",
        "drive_train": "All-wheel Drive",
        "mpg": "23–31 Based on EPA mileage ratings. Use for comparison purposes only. Actual mileage will vary depending on driving conditions, driving habits, vehicle maintenance, and other factors.",
        "fuel_type": "Gasoline",
        "transmission": "8-Speed Automatic",
        "engine": "2.0L I4 16V GDI DOHC Turbo",
        "price_USD": 21977.0,
        "url": "https://cars.com/vehicledetail/c7e6e1d4-86db-43b1-87a8-c388f14e1112/"
    },
    {
        "year_manufacture": 2013,
        "years": 12,
        "make": "mini",
        "model": "MINI Roadster Cooper S",
        "mileage": 89662.0,
        "stock_type": "Used",
        "interior_color": "Black",
        "exterior_color": "Midnight Black Metallic",
        "drive_train": "Front-wheel Drive",
        "mpg": "26–34 Based on EPA mileage ratings. Use for comparison purposes only. Actual mileage will vary depending on driving conditions, driving habits, vehicle maintenance, and other factors.",
        "fuel_type": "Gasoline",
        "transmission": "Automatic",
        "engine": "1.6L I-4 gasoline direct injection, DOHC, variable valve control",
        "price_USD": 13989.0,
        "url": "https://cars.com/vehicledetail/bc38eab3-a9fc-404b-a55b-284174012fa7/"
    },
    {
        "year_manufacture": 2015,
        "years": 10,
        "make": "mini",
        "model": "MINI Roadster Cooper S",
        "mileage": 54295.0,
        "stock_type": "Used",
        "interior_color": "Carbon Black",
        "exterior_color": "Chili Red",
        "drive_train": "Front-wheel Drive",
        "mpg": "25–35 Based on EPA mileage ratings. Use for comparison purposes only. Actual mileage will vary depending on driving conditions, driving habits, vehicle maintenance, and other factors.",
        "fuel_type": "Gasoline",
        "transmission": "Manual",
        "engine": "1.6L I-4 gasoline direct injection, DOHC, variable valve control",
        "price_USD": 15998.0,
        "url": "https://cars.com/vehicledetail/13c2e2e8-b4e9-4976-a041-372b2357a41c/"
    },
    {
        "year_manufacture": 2014,
        "years": 11,
        "make": "mini",
        "model": "MINI Convertible S",
        "mileage": 65020.0,
        "stock_type": "Used",
        "interior_color": "BLACK",
        "exterior_color": "Silver",
        "drive_train": "Rear-wheel Drive",
        "mpg": "26–35 Based on EPA mileage ratings. Use for comparison purposes only. Actual mileage will vary depending on driving conditions, driving habits, vehicle maintenance, and other factors.",
        "fuel_type": "Gasoline",
        "transmission": "Automatic",
        "engine": "Turbo Gas",
        "price_USD": 15998.0,
        "url": "https://cars.com/vehicledetail/9fac2e0d-77f5-4737-95b4-dd78deca9dcb/"
    },
    {
        "year_manufacture": 2019,
        "years": 6,
        "make": "mini",
        "model": "MINI E Countryman Cooper S ALL4",
        "mileage": 36318.0,
        "stock_type": "Used",
        "interior_color": "Carbon Black",
        "exterior_color": "Midnight Black",
        "drive_train": "All-wheel Drive",
        "mpg": "0–0 Based on EPA mileage ratings. Use for comparison purposes only. Actual mileage will vary depending on driving conditions, driving habits, vehicle maintenance, and other factors.",
        "fuel_type": "Gasoline",
        "transmission": "Automatic",
        "engine": "1.5L I-3 gasoline direct injection, DOHC, variable valve control",
        "price_USD": 23900.0,
        "url": "https://cars.com/vehicledetail/8aa84a67-3767-4851-8c7e-991b727cd2b0/"
    },
    {
        "year_manufacture": 2017,
        "years": 8,
        "make": "mini",
        "model": "MINI Convertible Cooper S",
        "mileage": 56533.0,
        "stock_type": "Used",
        "interior_color": "Brown",
        "exterior_color": "Blue",
        "drive_train": "Front-wheel Drive",
        "mpg": "23–33 Based on EPA mileage ratings. Use for comparison purposes only. Actual mileage will vary depending on driving conditions, driving habits, vehicle maintenance, and other factors.",
        "fuel_type": "Gasoline",
        "transmission": "Automatic 6-Speed",
        "engine": "2L I-4 gasoline direct injection, DOHC, variable valve control,",
        "price_USD": 18195.0,
        "url": "https://cars.com/vehicledetail/44538694-2351-4f1f-9ee2-d5cb2c2ce0be/"
    },
    {
        "year_manufacture": 2016,
        "years": 9,
        "make": "mini",
        "model": "MINI Hardtop",
        "mileage": 43369.0,
        "stock_type": "Used",
        "interior_color": "BLACK",
        "exterior_color": "Blue",
        "drive_train": "Rear-wheel Drive",
        "mpg": "28–39 Based on EPA mileage ratings. Use for comparison purposes only. Actual mileage will vary depending on driving conditions, driving habits, vehicle maintenance, and other factors.",
        "fuel_type": "Gasoline",
        "transmission": "Automatic",
        "engine": "Turbo Gas",
        "price_USD": 15998.0,
        "url": "https://cars.com/vehicledetail/5b7c2692-5927-4766-86de-71f0664b1fab/"
    },
    {
        "year_manufacture": 2011,
        "years": 14,
        "make": "mini",
        "model": "MINI Cooper Base",
        "mileage": 87421.0,
        "stock_type": "Used",
        "interior_color": "Black",
        "exterior_color": "Blue",
        "drive_train": "Front-wheel Drive",
        "mpg": "28–37 Based on EPA mileage ratings. Use for comparison purposes only. Actual mileage will vary depending on driving conditions, driving habits, vehicle maintenance, and other factors.",
        "fuel_type": "Gasoline",
        "transmission": "Automatic",
        "engine": "1.6L I-4 DOHC, variable valve control, premium unleaded, engine",
        "price_USD": 7999.0,
        "url": "https://cars.com/vehicledetail/e4d49a2e-56a5-432b-81fb-8e7faa329acb/"
    },
    {
        "year_manufacture": 2021,
        "years": 4,
        "make": "mini",
        "model": "MINI John Cooper Works GP Base",
        "mileage": 33614.0,
        "stock_type": "Used",
        "interior_color": "Carbon Black",
        "exterior_color": "Racing Gray Metallic",
        "drive_train": "Front-wheel Drive",
        "mpg": "24–30 Based on EPA mileage ratings. Use for comparison purposes only. Actual mileage will vary depending on driving conditions, driving habits, vehicle maintenance, and other factors.",
        "fuel_type": "Gasoline",
        "transmission": "Automatic",
        "engine": "2L I-4 gasoline direct injection, DOHC, variable valve control,",
        "price_USD": 37950.0,
        "url": "https://cars.com/vehicledetail/6fbf4f74-4af5-4194-ba8a-364590a6863c/"
    },
    {
        "year_manufacture": 2020,
        "years": 5,
        "make": "mini",
        "model": "MINI Clubman S ALL4",
        "mileage": 46412.0,
        "stock_type": "Used",
        "interior_color": "BLACK",
        "exterior_color": "Black",
        "drive_train": "Four-wheel Drive",
        "mpg": "23–32 Based on EPA mileage ratings. Use for comparison purposes only. Actual mileage will vary depending on driving conditions, driving habits, vehicle maintenance, and other factors.",
        "fuel_type": "Gasoline",
        "transmission": "Automatic",
        "engine": "Turbo Gas",
        "price_USD": 19998.0,
        "url": "https://cars.com/vehicledetail/b642b963-a999-4ea8-8d24-6d435288a1e0/"
    }
]