[
    {
        "year_manufacture": 2022,
        "years": 3,
        "make": "audi",
        "model": "Audi A6 allroad 2.0T Premium Plus",
        "mileage": 35752.0,
        "stock_type": "Audi Certified",
        "interior_color": "Black",
        "exterior_color": "Mythos Black Metallic",
        "drive_train": "All-wheel Drive",
        "mpg": "21–28 Based on EPA mileage ratings. Use for comparison purposes only. Actual mileage will vary depending on driving conditions, driving habits, vehicle maintenance, and other factors.",
        "fuel_type": "Hybrid",
        "transmission": "Automatic",
        "engine": "Intercooled Turbo Gas/Electric V-6 3.0 L/183",
        "price_USD": 52487.0,
        "url": "https://cars.com/vehicledetail/8740274c-d398-4efd-8518-a31b2c7b1d0a/?attribution_type=premier"
    },
    {
        "year_manufacture": 2013,
        "years": 12,
        "make": "audi",
        "model": "Audi allroad 2.0T Premium Plus",
        "mileage": 116671.0,
        "stock_type": "Used",
        "interior_color": "Black",
        "exterior_color": "Brilliant Black",
        "drive_train": "All-wheel Drive",
        "mpg": "20–29 Based on EPA mileage ratings. Use for comparison purposes only. Actual mileage will vary depending on driving conditions, driving habits, vehicle maintenance, and other factors.",
        "fuel_type": "Gasoline",
        "transmission": "Automatic",
        "engine": "2L I-4 gasoline direct injection, DOHC, variable valve control,",
        "price_USD": 9995.0,
        "url": "https://cars.com/vehicledetail/b99107f2-d805-44f0-b5c2-e414dd59e75c/"
    },
    {
        "year_manufacture": 2024,
        "years": 1,
        "make": "audi",
        "model": "Audi RS 6 Avant performance",
        "mileage": 9772.0,
        "stock_type": "Used",
        "interior_color": "Black/Blue",
        "exterior_color": "Nardo Gray",
        "drive_train": "All-wheel Drive",
        "mpg": "14–22 Based on EPA mileage ratings. Use for comparison purposes only. Actual mileage will vary depending on driving conditions, driving habits, vehicle maintenance, and other factors.",
        "fuel_type": "Hybrid",
        "transmission": "Automatic",
        "engine": "Twin Turbo Gas/Electric V-8 4.0 L/244",
        "price_USD": 132995.0,
        "url": "https://cars.com/vehicledetail/b31f191a-2af9-4152-bd5b-46f2e45672db/"
    },
    {
        "year_manufacture": 2019,
        "years": 6,
        "make": "audi",
        "model": "Audi S4 3.0T Premium",
        "mileage": 71020.0,
        "stock_type": "Used",
        "interior_color": "Rotor Gray",
        "exterior_color": "Gray",
        "drive_train": "All-wheel Drive",
        "mpg": "21–30 Based on EPA mileage ratings. Use for comparison purposes only. Actual mileage will vary depending on driving conditions, driving habits, vehicle maintenance, and other factors.",
        "fuel_type": "Gasoline",
        "transmission": "Automatic",
        "engine": "3L V-6 gasoline direct injection, DOHC, variable valve control,",
        "price_USD": 27980.0,
        "url": "https://cars.com/vehicledetail/e6b191a0-88cb-42a9-9ba7-1ab794249c20/"
    },
    {
        "year_manufacture": 2000,
        "years": 25,
        "make": "audi",
        "model": "Audi TT Coupe 2D",
        "mileage": 62843.0,
        "stock_type": "Used",
        "interior_color": "Ebony",
        "exterior_color": "Lake Silver Metallic",
        "drive_train": "Front-wheel Drive",
        "mpg": "22–29 Based on EPA mileage ratings. Use for comparison purposes only. Actual mileage will vary depending on driving conditions, driving habits, vehicle maintenance, and other factors.",
        "fuel_type": "Gasoline",
        "transmission": "Manual",
        "engine": "1.8L I-4 DOHC, intercooled turbo, premium unleaded, engine with",
        "price_USD": 10500.0,
        "url": "https://cars.com/vehicledetail/aaacde37-8208-48ff-ac8e-e80f9461e71c/"
    },
    {
        "year_manufacture": 2024,
        "years": 1,
        "make": "audi",
        "model": "Audi A3 Premium Plus",
        "mileage": 14231.0,
        "stock_type": "Used",
        "interior_color": "Black",
        "exterior_color": "Navarra Blue Metallic",
        "drive_train": "All-wheel Drive",
        "mpg": "27–34 Based on EPA mileage ratings. Use for comparison purposes only. Actual mileage will vary depending on driving conditions, driving habits, vehicle maintenance, and other factors.",
        "fuel_type": "Gasoline",
        "transmission": "quattro, s-tronic",
        "engine": "I4",
        "price_USD": 30610.0,
        "url": "https://cars.com/vehicledetail/ce1e80dc-4d60-4170-b2e6-a67e12875db8/"
    },
    {
        "year_manufacture": 2024,
        "years": 1,
        "make": "audi",
        "model": "Audi Q4 e-tron 55 quattro Premium",
        "mileage": 1995.0,
        "stock_type": "Used",
        "interior_color": "Gray",
        "exterior_color": "Navarra Blue Metallic",
        "drive_train": "All-wheel Drive",
        "mpg": "107–92 Based on EPA mileage ratings. Use for comparison purposes only. Actual mileage will vary depending on driving conditions, driving habits, vehicle maintenance, and other factors.",
        "fuel_type": "–",
        "transmission": "Single-speed transmission",
        "engine": "0.0L",
        "price_USD": 42795.0,
        "url": "https://cars.com/vehicledetail/16651411-fb9f-47e3-9ff0-7df12ecd6f7d/"
    },
    {
        "year_manufacture": 2019,
        "years": 6,
        "make": "audi",
        "model": "Audi e-tron Premium Plus",
        "mileage": 57760.0,
        "stock_type": "Used",
        "interior_color": "Black w/Rock Gray Stitch",
        "exterior_color": "Galaxy Blue Metallic",
        "drive_train": "All-wheel Drive",
        "mpg": null,
        "fuel_type": null,
        "transmission": "Automatic",
        "engine": "Electric",
        "price_USD": 26998.0,
        "url": "https://cars.com/vehicledetail/f278b863-8398-4704-b503-72a388ae493a/"
    },
    {
        "year_manufacture": 2024,
        "years": 1,
        "make": "audi",
        "model": "Audi A5 Sportback 45 S Line Premium Plus",
        "mileage": 9345.0,
        "stock_type": "Used",
        "interior_color": "Black",
        "exterior_color": "Glacier White Metallic",
        "drive_train": "All-wheel Drive",
        "mpg": "24–32 Based on EPA mileage ratings. Use for comparison purposes only. Actual mileage will vary depending on driving conditions, driving habits, vehicle maintenance, and other factors.",
        "fuel_type": "Gasoline",
        "transmission": "Automatic",
        "engine": "2L I-4 gasoline direct injection, DOHC, variable valve control,",
        "price_USD": 42786.0,
        "url": "https://cars.com/vehicledetail/48229a0c-f6f3-4b34-a7ad-fbcc7ce17c59/"
    },
    {
        "year_manufacture": 2022,
        "years": 3,
        "make": "audi",
        "model": "Audi A4 45 S line Premium Plus",
        "mileage": 58071.0,
        "stock_type": "Used",
        "interior_color": "Black",
        "exterior_color": "Ibis White",
        "drive_train": "All-wheel Drive",
        "mpg": "24–31 Based on EPA mileage ratings. Use for comparison purposes only. Actual mileage will vary depending on driving conditions, driving habits, vehicle maintenance, and other factors.",
        "fuel_type": "Gasoline",
        "transmission": "7-Speed Automatic with Auto-Shift",
        "engine": "2.0L I4 16V GDI DOHC Turbo",
        "price_USD": 24820.0,
        "url": "https://cars.com/vehicledetail/e06fec90-f4b0-4f4e-b89c-6eea96f95cbb/"
    },
    {
        "year_manufacture": 2002,
        "years": 23,
        "make": "audi",
        "model": "Audi TT Roadster quattro",
        "mileage": 160042.0,
        "stock_type": "Used",
        "interior_color": "Aviator Gray",
        "exterior_color": "White",
        "drive_train": "All-wheel Drive",
        "mpg": "20–28 Based on EPA mileage ratings. Use for comparison purposes only. Actual mileage will vary depending on driving conditions, driving habits, vehicle maintenance, and other factors.",
        "fuel_type": "Gasoline",
        "transmission": "Manual",
        "engine": "1.8L I-4 DOHC, intercooled turbo, premium unleaded, engine with",
        "price_USD": 5995.0,
        "url": "https://cars.com/vehicledetail/9ab9daed-a34d-4f54-8907-0200cae8d6e3/"
    },
    {
        "year_manufacture": 2019,
        "years": 6,
        "make": "audi",
        "model": "Audi A5 2.0T Prestige",
        "mileage": 60852.0,
        "stock_type": "Used",
        "interior_color": "Rock Gray",
        "exterior_color": "Mythos Black Metallic/Black Roof",
        "drive_train": "All-wheel Drive",
        "mpg": "23–34 Based on EPA mileage ratings. Use for comparison purposes only. Actual mileage will vary depending on driving conditions, driving habits, vehicle maintenance, and other factors.",
        "fuel_type": "Gasoline",
        "transmission": "Automatic",
        "engine": "2L I-4 gasoline direct injection, DOHC, variable valve control,",
        "price_USD": 28993.0,
        "url": "https://cars.com/vehicledetail/8fd5095c-20d2-41f0-8261-bbe083ff9f5a/"
    },
    {
        "year_manufacture": 2023,
        "years": 2,
        "make": "audi",
        "model": "Audi Q5 S-Line Premium Plus",
        "mileage": 34385.0,
        "stock_type": "Used",
        "interior_color": "BLACK",
        "exterior_color": "White",
        "drive_train": "Four-wheel Drive",
        "mpg": "23–29 Based on EPA mileage ratings. Use for comparison purposes only. Actual mileage will vary depending on driving conditions, driving habits, vehicle maintenance, and other factors.",
        "fuel_type": "Gasoline",
        "transmission": "Automatic",
        "engine": "Turbo Gas",
        "price_USD": 32998.0,
        "url": "https://cars.com/vehicledetail/ccfc8c76-c8d6-4501-8fe5-115a8737a0e4/"
    },
    {
        "year_manufacture": 2022,
        "years": 3,
        "make": "audi",
        "model": "Audi SQ5 3.0T Premium",
        "mileage": 41413.0,
        "stock_type": "Used",
        "interior_color": "Black",
        "exterior_color": "Ultra Blue Metallic",
        "drive_train": "All-wheel Drive",
        "mpg": "19–24 Based on EPA mileage ratings. Use for comparison purposes only. Actual mileage will vary depending on driving conditions, driving habits, vehicle maintenance, and other factors.",
        "fuel_type": "Gasoline",
        "transmission": "Automatic",
        "engine": "3.0L V6 24V GDI DOHC Turbo",
        "price_USD": 38821.0,
        "url": "https://cars.com/vehicledetail/8d59f5a0-5fd1-4d27-9777-3a41499d2a91/"
    },
    {
        "year_manufacture": 2023,
        "years": 2,
        "make": "audi",
        "model": "Audi S5 3.0T Prestige",
        "mileage": 34362.0,
        "stock_type": "Used",
        "interior_color": "Black",
        "exterior_color": "Tango Red Metallic",
        "drive_train": "All-wheel Drive",
        "mpg": "21–30 Based on EPA mileage ratings. Use for comparison purposes only. Actual mileage will vary depending on driving conditions, driving habits, vehicle maintenance, and other factors.",
        "fuel_type": "Gasoline",
        "transmission": "Automatic",
        "engine": "3.0L V6 24V GDI DOHC Turbo",
        "price_USD": 49900.0,
        "url": "https://cars.com/vehicledetail/93006ec4-8622-4a40-ae19-917a3f369cbc/"
    },
    {
        "year_manufacture": 2021,
        "years": 4,
        "make": "audi",
        "model": "Audi A8 L 60",
        "mileage": 27923.0,
        "stock_type": "Used",
        "interior_color": "Black",
        "exterior_color": "Vesuvius Gray Metallic",
        "drive_train": "All-wheel Drive",
        "mpg": "15–23 Based on EPA mileage ratings. Use for comparison purposes only. Actual mileage will vary depending on driving conditions, driving habits, vehicle maintenance, and other factors.",
        "fuel_type": "Gasoline",
        "transmission": "Automatic",
        "engine": "4L V-8 gasoline direct injection, DOHC, variable valve control,",
        "price_USD": 57998.0,
        "url": "https://cars.com/vehicledetail/3067a58b-d259-4bc2-be66-abc97135b098/"
    },
    {
        "year_manufacture": 2024,
        "years": 1,
        "make": "audi",
        "model": "Audi A4 45 S line Premium",
        "mileage": 7215.0,
        "stock_type": "Audi Certified",
        "interior_color": "Atlas Beige",
        "exterior_color": "Mythos Black Metallic",
        "drive_train": "All-wheel Drive",
        "mpg": "24–32 Based on EPA mileage ratings. Use for comparison purposes only. Actual mileage will vary depending on driving conditions, driving habits, vehicle maintenance, and other factors.",
        "fuel_type": "Gasoline",
        "transmission": "Auto-Shift Manual",
        "engine": "2L I-4 gasoline direct injection, DOHC, variable valve control,",
        "price_USD": 38765.0,
        "url": "https://cars.com/vehicledetail/1d1a36ed-90d9-4f23-b343-60dcfaa8dfd9/"
    },
    {
        "year_manufacture": 2023,
        "years": 2,
        "make": "audi",
        "model": "Audi S4 Premium Plus TFSI quattro Tiptronic",
        "mileage": 9344.0,
        "stock_type": "Audi Certified",
        "interior_color": "Black",
        "exterior_color": "Mythos Black Metallic",
        "drive_train": "All-wheel Drive",
        "mpg": "21–30 Based on EPA mileage ratings. Use for comparison purposes only. Actual mileage will vary depending on driving conditions, driving habits, vehicle maintenance, and other factors.",
        "fuel_type": "Gasoline",
        "transmission": "Automatic",
        "engine": "3L V-6 gasoline direct injection, DOHC, variable valve control,",
        "price_USD": 48978.0,
        "url": "https://cars.com/vehicledetail/e5ce438b-d03a-4f86-8415-6bf429df2a34/"
    },
    {
        "year_manufacture": 2018,
        "years": 7,
        "make": "audi",
        "model": "Audi A4 allroad 2.0T Premium",
        "mileage": 86864.0,
        "stock_type": "Used",
        "interior_color": "Nougat Brown / Black",
        "exterior_color": "Florett Silver Metallic",
        "drive_train": "All-wheel Drive",
        "mpg": "22–30 Based on EPA mileage ratings. Use for comparison purposes only. Actual mileage will vary depending on driving conditions, driving habits, vehicle maintenance, and other factors.",
        "fuel_type": "Gasoline",
        "transmission": "7-Speed Automatic with Auto-Shift",
        "engine": "2.0L I4 16V GDI DOHC Turbo",
        "price_USD": 19617.0,
        "url": "https://cars.com/vehicledetail/420eec29-4b26-4a36-9055-1ac9ae5bcdc0/"
    },
    {
        "year_manufacture": 2015,
        "years": 10,
        "make": "audi",
        "model": "Audi A4 2.0T Premium Plus",
        "mileage": 103993.0,
        "stock_type": "Used",
        "interior_color": "Black",
        "exterior_color": "Black",
        "drive_train": "All-wheel Drive",
        "mpg": "22–31 Based on EPA mileage ratings. Use for comparison purposes only. Actual mileage will vary depending on driving conditions, driving habits, vehicle maintenance, and other factors.",
        "fuel_type": "Gasoline",
        "transmission": "Automatic",
        "engine": "2L I-4 gasoline direct injection, DOHC, variable valve control,",
        "price_USD": 11750.0,
        "url": "https://cars.com/vehicledetail/472c1ba9-bced-41f0-a73a-d25c46fd5272/"
    },
    {
        "year_manufacture": 2018,
        "years": 7,
        "make": "audi",
        "model": "Audi R8 5.2 V10 plus",
        "mileage": 44998.0,
        "stock_type": "Used",
        "interior_color": "Black / Silver Stitching",
        "exterior_color": "Florett Silver Metallic",
        "drive_train": "All-wheel Drive",
        "mpg": "14–22 Based on EPA mileage ratings. Use for comparison purposes only. Actual mileage will vary depending on driving conditions, driving habits, vehicle maintenance, and other factors.",
        "fuel_type": "Gasoline",
        "transmission": "7-Speed Automatic S tronic",
        "engine": "5.2L V-10 port/direct injection, DOHC, variable valve control, p",
        "price_USD": 129947.0,
        "url": "https://cars.com/vehicledetail/5f3ead92-193e-47e8-bdc8-8f499a334f06/"
    }
]